twip/__init__.py
twip/constant.py
twip/cosine_distance.py
twip/features.py
twip/nlp.py
twip/plot.py
twip/settings.py
twip/settings_template.py
twip/train.py
twip/tweets.py
twip/urls.py
twip/util.py
twip/wsgi.py
twip/scripts/__init__.py
twip/scripts/cat_tweets.py
twip/scripts/clean.py
twip/scripts/explore.py
twip/scripts/generate.py
twip/scripts/plot_globe.py
twip/scripts/skeleton.py
twip/wip/build_pycon_slides.py
twip-0.0.14.dist-info/DESCRIPTION.rst
twip-0.0.14.dist-info/METADATA
twip-0.0.14.dist-info/RECORD
twip-0.0.14.dist-info/WHEEL
twip-0.0.14.dist-info/entry_points.txt
twip-0.0.14.dist-info/metadata.json
twip-0.0.14.dist-info/top_level.txt
