Metadata-Version: 2.0
Name: twip
Version: 0.0.14
Summary: Tweet Impact Predictor
Home-page: https://github.com/totalgood/twip/
Author: Hobson Lane
Author-email: twip@totalgood.com
License: mitrom
Platform: UNKNOWN
Requires-Dist: editdistance (==0.3.1)
Requires-Dist: future (==0.15.2)
Requires-Dist: gensim (==0.12.4)
Requires-Dist: ipython[all] (==4.2.0)
Requires-Dist: matplotlib (==1.5.1)
Requires-Dist: nltk (==3.2.1)
Requires-Dist: pandas (==0.18.1)
Requires-Dist: pandas-profiling (==1.0.0a2)
Requires-Dist: pug-nlp (>=0.1.14)
Requires-Dist: scikit-learn (==0.17.1)
Requires-Dist: seaborn (==0.7.0)
Requires-Dist: twython (==3.4.0)
